multi_mips/controller/controller.v
module Controller
(input clk, reset,
input [5:0] Opcode, Funct,
input zero,
output reg MemToReg, RegDst, IorD, PCSrc, ALUSrcA, ALUSrcB, IRWrite, MemWrite, PCWrite, Branch, RegWrite, ALUControl
);

//??? in pdf
reg [1:0] ALUOp;

//CONSTANTS
parameter LW=6'b100011;
parameter SW=6'b101011;

//state declartion
reg [2:0] state_reg, next_state; //2 bits for 3 states  - not one-hot encoding

parameter S0=0; //fetch/reset
parameter S1=1; //decode
parameter S2=2; //MemAdr
parameter S3=3; //MemRead
parameter S4=4; //MemWriteBack


always @(posedge clk or posedge reset) begin
	if(reset) state_reg <= S0;
	else state_reg <= next_state;
end

always @(state_reg) begin
	case(state_reg)
		S0:
			next_state = S1;
		S1: begin
			if (Opcode == LW) next_state = S2; //next
			else if(Opcode == SW) next_state = S2; //next
			else next_state=S1; //loopback...?
			end
		S2: begin
			if(Opcode == LW) next_state = S3; //next
			else next_state = S2; //loopback
			end
		S3:
			next_state = S4;
		S4:
			next_state = S0; //reset
	endcase
end

always @(state_reg) begin
	case(state_reg)
		S0: begin//fetch
			IorD = 0;
			ALUSrcA=0;
			ALUSrcB=2'b01;
			ALUOp=2'b00;
			PCSrc=0;
			IRWrite=1;
			PCWrite=1;
			end
		S1: begin //decode
			IorD = 1'bx;
			ALUSrcA=1'bx;
			ALUSrcB=2'bxx;
			ALUOp=2'b00;
			PCSrc=1'bx;
			IRWrite=0;
			PCWrite=0; 
			Branch=0;
			end
		S2: begin //MemAdr
			ALUSrcA=1;
			ALUSrcB=2'b10;
			ALUOp=2'b00;
			RegWrite=0;
			MemWrite=0;
			end
		S3: begin //MemRead
			IorD=1;
			end
		S4: begin //Mem WriteBack
			RegDst=0;
			MemToReg=1;
			RegWrite=1;
			end
	endcase
end

endmodule

multi_mips/controller/controller_tb.v
`include "controller.v"
module Controller_tb();

reg clk, reset;
reg [5:0] Opcode, Funct;
reg zero;
wire MemToReg, RegDst, IorD, PCSrc, ALUSrcA, ALUSrcB, IRWrite, MemWrite, PCWrite, Branch, RegWrite, ALUControl;

Controller controller (clk, reset, Opcode, Funct, //end of inputs
	MemToReg, RegDst, IorD, PCSrc, PCEn, ALUSrcA, ALUSrcB, 
	IRWrite, MemWrite, PCWrite, Branch, RegWrite, ALUControl
	);
	
initial begin
	clk=0;
	Opcode=6'b100011; //lw
	Funct=0;
	
	@(posedge clk) reset=1;
	@(posedge clk) reset=0;
	@(posedge clk) reset=0;
	@(posedge clk) reset=0;
	@(posedge clk) reset=0; Opcode=0;
	@(posedge clk) reset=0;
	@(posedge clk) reset=0;
	@(posedge clk) reset=0;
	@(posedge clk) reset=0;
	@(posedge clk) reset=0;
	@(posedge clk) reset=0;
	$finish;
	
end

initial begin
    $dumpfile("controller_tb.vcd");
    $dumpvars(0,Controller_tb);
 end

always #10 clk=~clk;


endmodule


//iverilog -o controller_tb controller_tb.v && ./controller_tb

multi_mips/controller/controller_tb.vcd
$date
	Wed Apr  3 23:07:59 2013
$end
$version
	Icarus Verilog
$end
$timescale
	1s
$end
$scope module Controller_tb $end
$var wire 1 ! MemToReg $end
$var wire 1 " RegWrite $end
$var wire 1 # RegDst $end
$var wire 1 $ PCWrite $end
$var wire 1 % PCSrc $end
$var wire 1 & PCEn $end
$var wire 1 ' MemWrite $end
$var wire 1 ( IorD $end
$var wire 1 ) IRWrite $end
$var wire 1 * Branch $end
$var wire 1 + ALUSrcB $end
$var wire 1 , ALUSrcA $end
$var wire 1 - ALUControl $end
$var reg 6 . Funct [5:0] $end
$var reg 6 / Opcode [5:0] $end
$var reg 1 0 clk $end
$var reg 1 1 reset $end
$scope module controller $end
$var wire 6 2 Funct [5:0] $end
$var wire 6 3 Opcode [5:0] $end
$var wire 1 0 clk $end
$var wire 1 1 reset $end
$var wire 1 ! zero $end
$var reg 1 - ALUControl $end
$var reg 2 4 ALUOp [1:0] $end
$var reg 1 , ALUSrcA $end
$var reg 1 + ALUSrcB $end
$var reg 1 * Branch $end
$var reg 1 ) IRWrite $end
$var reg 1 % IorD $end
$var reg 1 # MemToReg $end
$var reg 1 ' MemWrite $end
$var reg 1 & PCSrc $end
$var reg 1 $ PCWrite $end
$var reg 1 ( RegDst $end
$var reg 1 " RegWrite $end
$var reg 3 5 next_state [2:0] $end
$var reg 3 6 state_reg [2:0] $end
$upscope $end
$upscope $end
$enddefinitions $end
#0
$dumpvars
bx 6
bx 5
bx 4
b100011 3
b0 2
x1
00
b100011 /
b0 .
x-
x,
x+
x*
x)
x(
x'
x&
x%
x$
x#
x"
z!
$end
#10
1$
1)
0&
b0 4
1+
0,
0%
b1 5
b0 6
11
10
#20
00
#30
b10 5
0*
0$
0)
x&
x+
x,
x%
b1 6
01
10
#40
00
#50
0'
0"
0+
1,
b11 5
b10 6
10
#60
00
#70
b100 5
1%
b11 6
10
#80
00
#90
1"
1#
0(
b0 5
b100 6
b0 /
b0 3
10
#100
00
#110
b1 5
1$
1)
0&
1+
0,
0%
b0 6
10
#120
00
#130
0$
0)
x&
x+
x,
x%
b1 6
10
